inventree_dynamic_template_functions/__init__.py
inventree_dynamic_template_functions/dynamic_template_functions_plugin.py
inventree_dynamic_template_functions/text_formatter.py
inventree_dynamic_template_functions/templatetags/__init__.py
inventree_dynamic_template_functions/templatetags/dynamic_layout.py
inventree_dynamic_template_functions_plugin-0.1.0.dist-info/licenses/LICENSE
inventree_dynamic_template_functions_plugin-0.1.0.dist-info/METADATA
inventree_dynamic_template_functions_plugin-0.1.0.dist-info/WHEEL
inventree_dynamic_template_functions_plugin-0.1.0.dist-info/entry_points.txt
inventree_dynamic_template_functions_plugin-0.1.0.dist-info/top_level.txt
inventree_dynamic_template_functions_plugin-0.1.0.dist-info/RECORD
