Metadata-Version: 2.4
Name: inventree-dynamic-template-functions-plugin
Version: 0.1.0
Summary: Some functions for dynamically formatting text
Home-page: https://github.com/mschaf/inventree-dynamic-template-functions-plugin
Author: Martin Schaflitzl
Author-email: dev@martin-sc.de
License: MIT
Keywords: inventree label template format text inventory dynamic width
Classifier: Programming Language :: Python :: 3
Classifier: Operating System :: OS Independent
Classifier: Framework :: InvenTree
Requires-Python: >=3.9
License-File: LICENSE
Requires-Dist: pyhyphen
Dynamic: author
Dynamic: author-email
Dynamic: classifier
Dynamic: description
Dynamic: description-content-type
Dynamic: home-page
Dynamic: keywords
Dynamic: license
Dynamic: license-file
Dynamic: requires-dist
Dynamic: requires-python
Dynamic: summary
